Workbook

Sheet Read me
A1: Taps for Rights: Budget template (categories only)
A2: Background document 6 · Water Care AI Hackathon · Track A6 · Modelled on the Global Affairs Canada (GAC) budget template
A3: SYNTHETIC TRAINING MATERIAL. Water Care, Taps for Rights, Nimbara and Sundara are fictional. No real budget figures are included. Information elsewhere in the pack has been deliberately altered to include errors for testing.
A5: What this is
A6: An empty budget in the shape GAC expects: the cost categories from Appendix C of the contribution agreement, detail lines, a year-by-year view, the funding rules, and the questions GAC's financial reviewers typically ask. There are no real figures. If your tool needs numbers (for example to test a budget-variance check), generate your own test data and label it as such.
A8: How to use it
A9: 1. Budget Detail: one row per cost line. Fill the yellow cells. Totals and the GAC / Water Care split calculate automatically. Row 6 is a format example only; delete or overwrite it.
A10: 2. Budget Summary: totals by Appendix C category pulled from Budget Detail, plus the 12% overhead and automatic checks against the agreement's rules.
A11: 3. Budget by Year: optional split of each category across project years 1 to 4 (April to March).
A12: 4. Agreement Rules: the budget rules from the agreement with clause references.
A13: 5. GAC Review Questions: what GAC's financial reviewers usually ask about each category, so your proposal tool can anticipate them.
A15: Legend
... A19: GAC's budget template and the agreement number the same categories differently (for example, travel is 1.6.1 in the template but 1.5.1 in Appendix C). Both codes are shown. Map carefully.

Sheet Budget Detail
A1: Budget detail lines
A2: Fill yellow cells. One row per cost line. Amounts in Canadian dollars.
A3: SYNTHETIC TRAINING MATERIAL. Water Care, Taps for Rights, Nimbara and Sundara are fictional. No real budget figures are included. Information elsewhere in the pack has been deliberately altered to include errors for testing.
A5: Appendix C line | B5: GAC template code | C5: Category | D5: Description of cost | E5: Country | F5: Activity code | G5: Unit | H5: Quantity | I5: Unit cost (CAD) | J5: % charged to project | K5: Frequency | L5: Total (CAD) | M5: GAC share % | N5: GAC (CAD) | O5: Water Care cash (CAD)
A6: 1.5.1 | B6: =IFERROR(INDEX('Budget Summary'!$B$7:$B$20,MATCH(A6,'Budget Summary'!$A$7:$A$20,0)),"") -> 1.6.1 | C6: =IFERROR(INDEX('Budget Summary'!$C$7:$C$20,MATCH(A6,'Budget Summary'!$A$7:$A$20,0)),"") -> Travel costs | D6: EXAMPLE ONLY: monitoring visits by district coordinator (local transport) | E6: Nimbara | F6: 1122.1 | G6: trip | H6: 4 | I6: 150 | J6: 1 | K6: 1 | L6: =IF(H6="","",H6*I6*IF(J6="",1,J6)*IF(K6="",1,K6)) -> 600 | M6: 0.905 | N6: =IF(L6="","",L6*M6) -> 543 | O6: =IF(L6="","",L6-N6) -> 57
B7: =IFERROR(INDEX('Budget Summary'!$B$7:$B$20,MATCH(A7,'Budget Summary'!$A$7:$A$20,0)),"") | C7: =IFERROR(INDEX('Budget Summary'!$C$7:$C$20,MATCH(A7,'Budget Summary'!$A$7:$A$20,0)),"") | L7: =IF(H7="","",H7*I7*IF(J7="",1,J7)*IF(K7="",1,K7)) | M7: 0.905 | N7: =IF(L7="","",L7*M7) | O7: =IF(L7="","",L7-N7)
B8: =IFERROR(INDEX('Budget Summary'!$B$7:$B$20,MATCH(A8,'Budget Summary'!$A$7:$A$20,0)),"") | C8: =IFERROR(INDEX('Budget Summary'!$C$7:$C$20,MATCH(A8,'Budget Summary'!$A$7:$A$20,0)),"") | L8: =IF(H8="","",H8*I8*IF(J8="",1,J8)*IF(K8="",1,K8)) | M8: 0.905 | N8: =IF(L8="","",L8*M8) | O8: =IF(L8="","",L8-N8)
B9: =IFERROR(INDEX('Budget Summary'!$B$7:$B$20,MATCH(A9,'Budget Summary'!$A$7:$A$20,0)),"") | C9: =IFERROR(INDEX('Budget Summary'!$C$7:$C$20,MATCH(A9,'Budget Summary'!$A$7:$A$20,0)),"") | L9: =IF(H9="","",H9*I9*IF(J9="",1,J9)*IF(K9="",1,K9)) | M9: 0.905 | N9: =IF(L9="","",L9*M9) | O9: =IF(L9="","",L9-N9)
B10: =IFERROR(INDEX('Budget Summary'!$B$7:$B$20,MATCH(A10,'Budget Summary'!$A$7:$A$20,0)),"") | C10: =IFERROR(INDEX('Budget Summary'!$C$7:$C$20,MATCH(A10,'Budget Summary'!$A$7:$A$20,0)),"") | L10: =IF(H10="","",H10*I10*IF(J10="",1,J10)*IF(K10="",1,K10)) | M10: 0.905 | N10: =IF(L10="","",L10*M10) | O10: =IF(L10="","",L10-N10)
B11: =IFERROR(INDEX('Budget Summary'!$B$7:$B$20,MATCH(A11,'Budget Summary'!$A$7:$A$20,0)),"") | C11: =IFERROR(INDEX('Budget Summary'!$C$7:$C$20,MATCH(A11,'Budget Summary'!$A$7:$A$20,0)),"") | L11: =IF(H11="","",H11*I11*IF(J11="",1,J11)*IF(K11="",1,K11)) | M11: 0.905 | N11: =IF(L11="","",L11*M11) | O11: =IF(L11="","",L11-N11)
B12: =IFERROR(INDEX('Budget Summary'!$B$7:$B$20,MATCH(A12,'Budget Summary'!$A$7:$A$20,0)),"") | C12: =IFERROR(INDEX('Budget Summary'!$C$7:$C$20,MATCH(A12,'Budget Summary'!$A$7:$A$20,0)),"") | L12: =IF(H12="","",H12*I12*IF(J12="",1,J12)*IF(K12="",1,K12)) | M12: 0.905 | N12: =IF(L12="","",L12*M12) | O12: =IF(L12="","",L12-N12)
B13: =IFERROR(INDEX('Budget Summary'!$B$7:$B$20,MATCH(A13,'Budget Summary'!$A$7:$A$20,0)),"") | C13: =IFERROR(INDEX('Budget Summary'!$C$7:$C$20,MATCH(A13,'Budget Summary'!$A$7:$A$20,0)),"") | L13: =IF(H13="","",H13*I13*IF(J13="",1,J13)*IF(K13="",1,K13)) | M13: 0.905 | N13: =IF(L13="","",L13*M13) | O13: =IF(L13="","",L13-N13)
B14: =IFERROR(INDEX('Budget Summary'!$B$7:$B$20,MATCH(A14,'Budget Summary'!$A$7:$A$20,0)),"") | C14: =IFERROR(INDEX('Budget Summary'!$C$7:$C$20,MATCH(A14,'Budget Summary'!$A$7:$A$20,0)),"") | L14: =IF(H14="","",H14*I14*IF(J14="",1,J14)*IF(K14="",1,K14)) | M14: 0.905 | N14: =IF(L14="","",L14*M14) | O14: =IF(L14="","",L14-N14)
B15: =IFERROR(INDEX('Budget Summary'!$B$7:$B$20,MATCH(A15,'Budget Summary'!$A$7:$A$20,0)),"") | C15: =IFERROR(INDEX('Budget Summary'!$C$7:$C$20,MATCH(A15,'Budget Summary'!$A$7:$A$20,0)),"") | L15: =IF(H15="","",H15*I15*IF(J15="",1,J15)*IF(K15="",1,K15)) | M15: 0.905 | N15: =IF(L15="","",L15*M15) | O15: =IF(L15="","",L15-N15)
B16: =IFERROR(INDEX('Budget Summary'!$B$7:$B$20,MATCH(A16,'Budget Summary'!$A$7:$A$20,0)),"") | C16: =IFERROR(INDEX('Budget Summary'!$C$7:$C$20,MATCH(A16,'Budget Summary'!$A$7:$A$20,0)),"") | L16: =IF(H16="","",H16*I16*IF(J16="",1,J16)*IF(K16="",1,K16)) | M16: 0.905 | N16: =IF(L16="","",L16*M16) | O16: =IF(L16="","",L16-N16)
B17: =IFERROR(INDEX('Budget Summary'!$B$7:$B$20,MATCH(A17,'Budget Summary'!$A$7:$A$20,0)),"") | C17: =IFERROR(INDEX('Budget Summary'!$C$7:$C$20,MATCH(A17,'Budget Summary'!$A$7:$A$20,0)),"") | L17: =IF(H17="","",H17*I17*IF(J17="",1,J17)*IF(K17="",1,K17)) | M17: 0.905 | N17: =IF(L17="","",L17*M17) | O17: =IF(L17="","",L17-N17)
B18: =IFERROR(INDEX('Budget Summary'!$B$7:$B$20,MATCH(A18,'Budget Summary'!$A$7:$A$20,0)),"") | C18: =IFERROR(INDEX('Budget Summary'!$C$7:$C$20,MATCH(A18,'Budget Summary'!$A$7:$A$20,0)),"") | L18: =IF(H18="","",H18*I18*IF(J18="",1,J18)*IF(K18="",1,K18)) | M18: 0.905 | N18: =IF(L18="","",L18*M18) | O18: =IF(L18="","",L18-N18)
... B80: =IFERROR(INDEX('Budget Summary'!$B$7:$B$20,MATCH(A80,'Budget Summary'!$A$7:$A$20,0)),"") | C80: =IFERROR(INDEX('Budget Summary'!$C$7:$C$20,MATCH(A80,'Budget Summary'!$A$7:$A$20,0)),"") | L80: =IF(H80="","",H80*I80*IF(J80="",1,J80)*IF(K80="",1,K80)) | M80: 0.905 | N80: =IF(L80="","",L80*M80) | O80: =IF(L80="","",L80-N80)
K81: Totals | L81: =SUM(L6:L80) -> 600 | N81: =SUM(N6:N80) -> 543 | O81: =SUM(O6:O80) -> 57

Sheet Budget Summary
A1: Budget summary by Appendix C category
A2: Pulled from Budget Detail. Enter in-kind amounts (if any) in the yellow column.
A3: SYNTHETIC TRAINING MATERIAL. Water Care, Taps for Rights, Nimbara and Sundara are fictional. No real budget figures are included. Information elsewhere in the pack has been deliberately altered to include errors for testing.
A6: Appendix C line | B6: GAC template code | C6: Summary of eligible cost categories | D6: Group | E6: The Department (GAC) | F6: Water Care cash | G6: Water Care in-kind | H6: Total
A7: 1.1 | B7: 1.1 | C7: Remuneration - Organization's employees (Canada / short-term overseas) | D7: Remuneration/Fees | E7: =SUMIFS('Budget Detail'!$N$6:$N$80,'Budget Detail'!$A$6:$A$80,A7) -> 0 | F7: =SUMIFS('Budget Detail'!$O$6:$O$80,'Budget Detail'!$A$6:$A$80,A7) -> 0 | H7: =SUM(E7:G7) -> 0
A8: 1.1b | B8: 1.1 | C8: Remuneration - Organization's employees on long-term assignment overseas | D8: Remuneration/Fees | E8: =SUMIFS('Budget Detail'!$N$6:$N$80,'Budget Detail'!$A$6:$A$80,A8) -> 0 | F8: =SUMIFS('Budget Detail'!$O$6:$O$80,'Budget Detail'!$A$6:$A$80,A8) -> 0 | H8: =SUM(E8:G8) -> 0
A9: 1.2 | B9: 1.2 | C9: Remuneration - Local employees | D9: Remuneration/Fees | E9: =SUMIFS('Budget Detail'!$N$6:$N$80,'Budget Detail'!$A$6:$A$80,A9) -> 0 | F9: =SUMIFS('Budget Detail'!$O$6:$O$80,'Budget Detail'!$A$6:$A$80,A9) -> 0 | H9: =SUM(E9:G9) -> 0
A10: 1.3a | B10: 1.4 | C10: Fees - Canadian and international subcontractors | D10: Remuneration/Fees | E10: =SUMIFS('Budget Detail'!$N$6:$N$80,'Budget Detail'!$A$6:$A$80,A10) -> 0 | F10: =SUMIFS('Budget Detail'!$O$6:$O$80,'Budget Detail'!$A$6:$A$80,A10) -> 0 | H10: =SUM(E10:G10) -> 0
A11: 1.3b | B11: 1.4 | C11: Fees - Local subcontractors | D11: Remuneration/Fees | E11: =SUMIFS('Budget Detail'!$N$6:$N$80,'Budget Detail'!$A$6:$A$80,A11) -> 0 | F11: =SUMIFS('Budget Detail'!$O$6:$O$80,'Budget Detail'!$A$6:$A$80,A11) -> 0 | H11: =SUM(E11:G11) -> 0
A12: 1.5.1 | B12: 1.6.1 | C12: Travel costs | D12: Reimbursable | E12: =SUMIFS('Budget Detail'!$N$6:$N$80,'Budget Detail'!$A$6:$A$80,A12) -> 543 | F12: =SUMIFS('Budget Detail'!$O$6:$O$80,'Budget Detail'!$A$6:$A$80,A12) -> 57 | H12: =SUM(E12:G12) -> 600
A13: 1.5.2 | B13: 1.6.2 | C13: Benefits and allowable expenses: long-term assignment / short-term relocation | D13: Reimbursable | E13: =SUMIFS('Budget Detail'!$N$6:$N$80,'Budget Detail'!$A$6:$A$80,A13) -> 0 | F13: =SUMIFS('Budget Detail'!$O$6:$O$80,'Budget Detail'!$A$6:$A$80,A13) -> 0 | H13: =SUM(E13:G13) -> 0
A14: 1.5.3 | B14: 1.6.3 | C14: Costs for students and trainees | D14: Reimbursable | E14: =SUMIFS('Budget Detail'!$N$6:$N$80,'Budget Detail'!$A$6:$A$80,A14) -> 0 | F14: =SUMIFS('Budget Detail'!$O$6:$O$80,'Budget Detail'!$A$6:$A$80,A14) -> 0 | H14: =SUM(E14:G14) -> 0
A15: 1.5.4 | B15: 1.6.4 | C15: Other training costs | D15: Reimbursable | E15: =SUMIFS('Budget Detail'!$N$6:$N$80,'Budget Detail'!$A$6:$A$80,A15) -> 0 | F15: =SUMIFS('Budget Detail'!$O$6:$O$80,'Budget Detail'!$A$6:$A$80,A15) -> 0 | H15: =SUM(E15:G15) -> 0
A16: 1.5.5 | B16: 1.6.6 | C16: Goods, assets and supplies | D16: Reimbursable | E16: =SUMIFS('Budget Detail'!$N$6:$N$80,'Budget Detail'!$A$6:$A$80,A16) -> 0 | F16: =SUMIFS('Budget Detail'!$O$6:$O$80,'Budget Detail'!$A$6:$A$80,A16) -> 0 | H16: =SUM(E16:G16) -> 0
A17: 1.5.6 | B17: 1.6.7 | C17: Project administration costs directly related to the Project | D17: Reimbursable | E17: =SUMIFS('Budget Detail'!$N$6:$N$80,'Budget Detail'!$A$6:$A$80,A17) -> 0 | F17: =SUMIFS('Budget Detail'!$O$6:$O$80,'Budget Detail'!$A$6:$A$80,A17) -> 0 | H17: =SUM(E17:G17) -> 0
A18: 1.5.7 | B18: 1.6.10 | C18: Other direct costs | D18: Reimbursable | E18: =SUMIFS('Budget Detail'!$N$6:$N$80,'Budget Detail'!$A$6:$A$80,A18) -> 0 | F18: =SUMIFS('Budget Detail'!$O$6:$O$80,'Budget Detail'!$A$6:$A$80,A18) -> 0 | H18: =SUM(E18:G18) -> 0
... A20: 1.5.8b | B20: 1.6.9 | C20: Construction: non-structural works | D20: Reimbursable | E20: =SUMIFS('Budget Detail'!$N$6:$N$80,'Budget Detail'!$A$6:$A$80,A20) -> 0 | F20: =SUMIFS('Budget Detail'!$O$6:$O$80,'Budget Detail'!$A$6:$A$80,A20) -> 0 | H20: =SUM(E20:G20) -> 0
C21: Sub-total: Remuneration/Fees | E21: =SUMIFS(E7:E20,$D$7:$D$20,"Remuneration/Fees") -> 0 | F21: =SUMIFS(F7:F20,$D$7:$D$20,"Remuneration/Fees") -> 0 | G21: =SUMIFS(G7:G20,$D$7:$D$20,"Remuneration/Fees") -> 0 | H21: =SUMIFS(H7:H20,$D$7:$D$20,"Remuneration/Fees") -> 0
C22: Sub-total: Reimbursable costs eligible for the fixed overhead rate | E22: =SUMIFS(E7:E20,$D$7:$D$20,"Reimbursable") -> 543 | F22: =SUMIFS(F7:F20,$D$7:$D$20,"Reimbursable") -> 57 | G22: =SUMIFS(G7:G20,$D$7:$D$20,"Reimbursable") -> 0 | H22: =SUMIFS(H7:H20,$D$7:$D$20,"Reimbursable") -> 600
C23: Total eligible direct costs (1.1 to 1.5) | E23: =E21+E22 -> 543 | F23: =F21+F22 -> 57 | G23: =G21+G22 -> 0 | H23: =H21+H22 -> 600
A24: 1.6 | B24: 1.9.1 | C24: Compensation for indirect/overhead costs (fixed rate on GAC share of 1.1 to 1.5) | E24: =E23*$E$34 -> 65.16 | H24: =E24 -> 65.16
C25: TOTAL CONTRIBUTION TO PROJECT | E25: =E23+E24 -> 608.16 | F25: =F23 -> 57 | G25: =G23 -> 0 | H25: =H23+H24 -> 665.16
C27: Assumptions (from the agreement)
C28: GAC maximum share of eligible direct costs | E28: 0.905 | F28: Source: Art. 2.1 b)
C29: Water Care minimum share of eligible direct costs (agreement) | E29: 0.095 | F29: Source: Art. 2.2 and 2.3
C30: Applicant minimum cost share (call for proposals) | E30: 0.1 | F30: Source: Call, project parameters; agreement Art. 2.4
C31: Maximum single-line transfer without GAC approval | E31: 0.2 | F31: Source: Appendix C 1.2.3
C32: Maximum subcontracting as share of GAC contribution | E32: 0.2 | F32: Source: Appendix B 1.3.2
C33: Construction threshold for the fixed overhead rate (share of GAC contribution) | E33: 0.2 | F33: Source: GAC budget template 1.6.9 / 1.7.1
C34: Overhead rate on GAC share of 1.1 to 1.5 | E34: 0.12 | F34: Source: Appendix B 1.6
C37: Automatic checks (blank until the budget has figures)
C38: Check | E38: Value | F38: Limit | H38: Result
C39: GAC share of eligible direct costs | E39: =IFERROR(E23/H23,"") -> 0.905 | F39: =E28 -> 0.905 | H39: =IF(E39="","",IF(E39<=F39,"OK","CHECK")) -> OK
C40: Water Care share of eligible direct costs vs agreement minimum | E40: =IFERROR((F23+G23)/H23,"") -> 0.095 | F40: =E29 -> 0.095 | H40: =IF(E40="","",IF(E40>=F40,"OK","CHECK")) -> OK
C41: Water Care share of eligible direct costs vs call minimum | E41: =IFERROR((F23+G23)/H23,"") -> 0.095 | F41: =E30 -> 0.1 | H41: =IF(E41="","",IF(E41>=F41,"OK","CHECK")) -> CHECK
C42: Subcontracting (1.3) as share of GAC contribution | E42: =IFERROR((E10+E11)/E25,"") -> 0 | F42: =E32 -> 0.2 | H42: =IF(E42="","",IF(E42<=F42,"OK","CHECK")) -> OK
C43: Construction (1.5.8) as share of GAC contribution | E43: =IFERROR((E19+E20)/E25,"") -> 0 | F43: =E33 -> 0.2 | H43: =IF(E43="","",IF(E43<=F43,"OK","CHECK")) -> OK

Sheet Budget by Year
A1: Budget by project year
A2: Project year = 1 April to 31 March. Year 1 starts on the Effective Date. Fill yellow cells; the check column compares with Budget Summary.
A3: SYNTHETIC TRAINING MATERIAL. Water Care, Taps for Rights, Nimbara and Sundara are fictional. No real budget figures are included. Information elsewhere in the pack has been deliberately altered to include errors for testing.
A5: Appendix C line | B5: Category | C5: Year 1 (2019-20) | D5: Year 2 (2020-21) | E5: Year 3 (2021-22) | F5: Year 4 (2022-23) | G5: Close-out (Apr to Sep 2023) | H5: Total | I5: Matches summary?
A6: 1.1 | B6: Remuneration - Organization's employees (Canada / short-term overseas) | H6: =SUM(C6:G6) -> 0 | I6: =IF(H6=0,"",IF(ABS(H6-'Budget Summary'!H7)<1,"Yes","No"))
A7: 1.1b | B7: Remuneration - Organization's employees on long-term assignment overseas | H7: =SUM(C7:G7) -> 0 | I7: =IF(H7=0,"",IF(ABS(H7-'Budget Summary'!H8)<1,"Yes","No"))
A8: 1.2 | B8: Remuneration - Local employees | H8: =SUM(C8:G8) -> 0 | I8: =IF(H8=0,"",IF(ABS(H8-'Budget Summary'!H9)<1,"Yes","No"))
A9: 1.3a | B9: Fees - Canadian and international subcontractors | H9: =SUM(C9:G9) -> 0 | I9: =IF(H9=0,"",IF(ABS(H9-'Budget Summary'!H10)<1,"Yes","No"))
A10: 1.3b | B10: Fees - Local subcontractors | H10: =SUM(C10:G10) -> 0 | I10: =IF(H10=0,"",IF(ABS(H10-'Budget Summary'!H11)<1,"Yes","No"))
A11: 1.5.1 | B11: Travel costs | H11: =SUM(C11:G11) -> 0 | I11: =IF(H11=0,"",IF(ABS(H11-'Budget Summary'!H12)<1,"Yes","No"))
A12: 1.5.2 | B12: Benefits and allowable expenses: long-term assignment / short-term relocation | H12: =SUM(C12:G12) -> 0 | I12: =IF(H12=0,"",IF(ABS(H12-'Budget Summary'!H13)<1,"Yes","No"))
A13: 1.5.3 | B13: Costs for students and trainees | H13: =SUM(C13:G13) -> 0 | I13: =IF(H13=0,"",IF(ABS(H13-'Budget Summary'!H14)<1,"Yes","No"))
A14: 1.5.4 | B14: Other training costs | H14: =SUM(C14:G14) -> 0 | I14: =IF(H14=0,"",IF(ABS(H14-'Budget Summary'!H15)<1,"Yes","No"))
A15: 1.5.5 | B15: Goods, assets and supplies | H15: =SUM(C15:G15) -> 0 | I15: =IF(H15=0,"",IF(ABS(H15-'Budget Summary'!H16)<1,"Yes","No"))
A16: 1.5.6 | B16: Project administration costs directly related to the Project | H16: =SUM(C16:G16) -> 0 | I16: =IF(H16=0,"",IF(ABS(H16-'Budget Summary'!H17)<1,"Yes","No"))
A17: 1.5.7 | B17: Other direct costs | H17: =SUM(C17:G17) -> 0 | I17: =IF(H17=0,"",IF(ABS(H17-'Budget Summary'!H18)<1,"Yes","No"))
... A19: 1.5.8b | B19: Construction: non-structural works | H19: =SUM(C19:G19) -> 0 | I19: =IF(H19=0,"",IF(ABS(H19-'Budget Summary'!H20)<1,"Yes","No"))

Sheet Agreement Rules
A1: Budget and payment rules in the contribution agreement
A2: Use these to build checks. Clause references point to the agreement in this pack.
A3: SYNTHETIC TRAINING MATERIAL. Water Care, Taps for Rights, Nimbara and Sundara are fictional. No real budget figures are included. Information elsewhere in the pack has been deliberately altered to include errors for testing.
A5: Rule | B5: Where | C5: Notes
A6: GAC contributes the lesser of the maximum amount and 90.5% of eligible direct costs, plus overhead. | B6: Articles 2.1 | C6: Art. 2.1 calls the budget Appendix B and payment terms Appendix C; Art. 1.3 lists them the other way round.
A7: Water Care contributes at least 9.5% of eligible direct costs (cash and/or in kind from Canadian sources). | B7: Article 2.2 | C7: Compare with Art. 2.3, Art. 2.4 and Appendix C 1.3.
A8: At the end of the Project, Water Care's contribution is at least 9.5% in cash from Canadian sources. | B8: Article 2.3
A9: Applicant provides at least 10% of total eligible direct costs (call parameter). | B9: Article 2.4; call
A10: Overhead: fixed 12% on GAC's contribution toward lines 1.1 to 1.5 only. | B10: Appendix B 1.6
A11: Subcontracting paid by GAC is capped at 20% of the GAC contribution. | B11: Appendix B 1.3.2
A12: Transfers between lines up to 20% need no approval if scope is unchanged. | B12: Appendix C 1.2.3
A13: Transfers above 20% of a line need GAC's prior written approval. | B13: Appendix C 1.2.2
A14: Any transfer into the Remuneration/Fees sub-total, or any change to Construction or Flow-through lines, needs an amendment. | B14: Appendix C 1.2.1
A15: Transfers can never increase the GAC contribution. | B15: Appendix C 1.2.4
A16: Advances are semi-annual, up to 95% of the contribution, and never more than two periods outstanding. | B16: Appendix B 2.2.2 and 2.2.4
A17: Foreign currency costs are converted by FIFO or weighted average only. | B17: Appendix B 2.2.5
A18: GAC funds are kept in an interest-bearing account; interest can be used only with prior written approval. | B18: Appendix B 2.2.6
A19: Construction needs an approved Construction Validation Plan before work starts. | B19: Appendix D 4.4
A20: Only demobilization, asset disposal and final reports are eligible after activities end (31 March 2023). | B20: Article 4.2

Sheet GAC Review Questions
A1: What GAC's financial reviewers typically ask
A2: Based on the kinds of questions raised in GAC budget reviews of similar projects. Names and figures removed.
A3: SYNTHETIC TRAINING MATERIAL. Water Care, Taps for Rights, Nimbara and Sundara are fictional. No real budget figures are included. Information elsewhere in the pack has been deliberately altered to include errors for testing.
A5: Budget category | B5: Typical question from GAC | C5: What to have ready
A6: 1.1 Organization's employees | B6: Provide an organizational chart, job descriptions and, if applicable, the collective agreement. Complete the salary table. Describe each employee's tasks on this project. | C6: Org chart; job descriptions; salary table with level of effort per role; task descriptions.
A7: 1.2 Local employees | B7: Complete the salary table. Why are some local salaries higher than Canadian salaries? | C7: Market-rate evidence; seniority of roles; level of effort of senior staff (often a small %).
A8: 1.3 Subcontractors | B8: Are these subcontractors or employees? If two positions come from the same subcontractor, confirm. Describe each subcontractor's tasks. | C8: Subcontractor task descriptions; arm's length status; daily rates and days.
A9: 1.5.1 Travel | B9: Who are the flights for, where are they going, and how many per year? Give units and unit costs for every line. Meal and incidental allowances must follow the NJC Travel Directive. | C9: Travel plan by traveller and trip; unit costs; NJC rates.
A10: 1.5.4 Other training | B10: Detail every cost line with units and unit costs, by country. | C10: Training plan; venue, materials and per-participant costs.
A11: 1.5.5 Goods, assets and supplies | B11: Detail every line with units and unit costs. A disposal plan is required before the end of the project for all assets with a lifespan over one year. | C11: Asset list with expected lifespan; % charged to project; disposal intentions.
A12: 1.5.6 Project administration | B12: Detail every line by country. Why is an item charged at 100% when related costs (e.g. rent) are charged at 40%? Which vehicle is insured? | C12: Consistent allocation percentages across related lines.
A13: 1.5.8 Construction | B13: Is construction below 20% of GAC's contribution? Which works are structural vs non-structural? Has a Construction Validation Plan been approved? | C13: Site list; works type; competent authority; CVP status.
A14: General | B14: Remuneration is a large share of the budget: justify. Do all detail tabs reconcile to the main budget? | C14: Reconciliation of every tab to the summary; rationale for staffing mix.
